caltool/__init__.py
caltool/utils.py
countool/__init__.py
cvisp/__init__.py
cvisp/utils.py
countool-0.0.4.dist-info/LICENSE.txt
countool-0.0.4.dist-info/METADATA
countool-0.0.4.dist-info/WHEEL
countool-0.0.4.dist-info/top_level.txt
countool-0.0.4.dist-info/RECORD
