Metadata-Version: 2.1
Name: countool
Version: 0.0.4
Summary: A small example package of calculator for params/macs 
Home-page: https://github.com/HuiiJi
Author: Huii Ji
Author-email: 752413464@qq.com
License: UNKNOWN
Platform: UNKNOWN
Classifier: Programming Language :: Python :: 3
Classifier: License :: OSI Approved :: MIT License
Classifier: Operating System :: OS Independent
Requires-Python: >=3.6
License-File: LICENSE.txt
Requires-Dist: torch
Requires-Dist: onnx-tool
Requires-Dist: thop
Requires-Dist: netron
